pcra/__init__.py
pcra/__main__.py
pcra/pcra.py
pcra/utils.py
pcra/template/.gitignore
pcra/template/README.md
pcra/template/asset.js.patch
pcra/template/asset.js.win.patch
pcra/template/dev-server.js
pcra/template/client/package.json
pcra/template/client/requirements.txt
pcra/template/client/src/app.py
pcra/template/client/src/index.html
pcra/template/client/src/version.py
pcra/template/client/src/common/__init__.py
pcra/template/client/src/common/jsutils.py
pcra/template/client/src/common/pymui.py
pcra/template/client/src/common/pyreact.py
pcra/template/client/src/common/urlutils.py
pcra/template/client/src/main/__init__.py
pcra/template/client/src/main/aboutModal.py
pcra/template/client/src/main/appData.py
pcra/template/client/src/main/appTheme.py
pcra/template/client/src/main/loginModal.py
pcra/template/client/src/static/app_logo.png
pcra/template/client/src/static/favicon.ico
pcra/template/client/src/views/__init__.py
pcra/template/client/src/views/landingPage/__init__.py
pcra/template/client/src/views/landingPage/landingPageMenu.py
pcra/template/client/src/views/landingPage/landingPageView.py
pcra/template/default/src/app.css
pcra/template/default/src/app.py
pcra/template/default/src/favicon.ico
pcra/template/default/src/index.html
pcra/template/default/src/python_logo.png
pcra/template/default/src/react_logo.png
pcra/template/server/admin_routes.py
pcra/template/server/appserver.py
pcra/template/server/requirements.txt
pcra-0.1.1.dist-info/LICENSE
pcra-0.1.1.dist-info/METADATA
pcra-0.1.1.dist-info/WHEEL
pcra-0.1.1.dist-info/entry_points.txt
pcra-0.1.1.dist-info/top_level.txt
pcra-0.1.1.dist-info/RECORD
