Metadata-Version: 2.1
Name: pcra
Version: 0.1.1
Summary: Python Create React App
Home-page: https://github.com/JennaSys/pcra
Author: John Sheehan
Author-email: jennasyseng@gmail.com
License: MIT
Keywords: react material-ui mui transcrypt cli web
Platform: UNKNOWN
Classifier: License :: OSI Approved :: MIT License
Classifier: Development Status :: 4 - Beta
Classifier: Intended Audience :: Developers
Classifier: Framework :: Flask
Classifier: Topic :: Software Development :: Libraries :: Application Frameworks
Classifier: Programming Language :: Python :: 3.7
Classifier: Operating System :: OS Independent
Classifier: Environment :: Console
Classifier: Natural Language :: English
Requires-Python: >=3.7,<3.8
Requires-Dist: patch
Requires-Dist: colorama
